README.md
setup.py
ncmdump/__init__.py
ncmdump/app.py
ncmdump/core.py
ncmdump.egg-info/PKG-INFO
ncmdump.egg-info/SOURCES.txt
ncmdump.egg-info/dependency_links.txt
ncmdump.egg-info/entry_points.txt
ncmdump.egg-info/not-zip-safe
ncmdump.egg-info/requires.txt
ncmdump.egg-info/top_level.txt