Metadata-Version: 1.2
Name: ncmdump
Version: 0.1.0
Summary: netease cloud music copyright protection file dump
Home-page: http://github.com/nondanee/ncmdump
Author: nondanee
Author-email: iminezn5656@outlook.com
License: MIT
Keywords: ncm,netease cloud music
Platform: any
Requires-Python: >=2.7, !=3.0.*, !=3.1.*, !=3.2.*, !=3.3.*
